.gitignore
.readthedocs.yml
.rtd-environment.yml
.travis.yml
CHANGES.rst
CITATION
CODE_OF_CONDUCT.md
CONTRIBUTING.md
Dockerfile
MANIFEST.in
README.rst
pyproject.toml
readthedocs.yml
setup.cfg
setup.py
caldp/__init__.py
caldp/_astropy_init.py
caldp/conftest.py
caldp/create_previews.py
caldp/log.py
caldp/main.py
caldp/process.py
caldp/version.py
caldp.egg-info/PKG-INFO
caldp.egg-info/SOURCES.txt
caldp.egg-info/dependency_links.txt
caldp.egg-info/not-zip-safe
caldp.egg-info/requires.txt
caldp.egg-info/top_level.txt
caldp/data/README.rst
caldp/extern/__init__.py
caldp/tests/__init__.py
caldp/tests/test_all.py
caldp/utils/__init__.py
caldp/utils/tests/__init__.py
docs/Makefile
docs/conf.py
docs/index.rst
docs/make.bat
docs/caldp/index.rst
licenses/AURA.rst
licenses/LICENSE.rst
licenses/README.rst
licenses/TEMPLATE_LICENCE.rst
scripts/caldp-cal-env
scripts/caldp-config-aws
scripts/caldp-config-offsite
scripts/caldp-config-onsite
scripts/caldp-docker-run-container
scripts/caldp-docker-run-pipeline
scripts/caldp-get-output-path
scripts/caldp-image-build
scripts/caldp-image-config
scripts/caldp-image-push
scripts/caldp-install-all
scripts/caldp-install-cal
scripts/caldp-install-conda
scripts/caldp-install-fitscut
scripts/caldp-process
scripts/caldp-process-aws