Metadata-Version: 2.1
Name: caldp
Version: 0.1.0
Summary: Calibration data pipeline for Hubble Space Telescope Observations
Home-page: http://stsci.edu
Author: STScI
Author-email: helpdesk@stsci.edu
License: BSD 3-Clause
Platform: UNKNOWN
Requires-Python: >=3.6
Provides-Extra: test
Provides-Extra: docs
Provides-Extra: dev
